latency_audit/__init__.py
latency_audit/cli.py
latency_audit/models.py
latency_audit/output.py
latency_audit/py.typed
latency_audit/runner.py
latency_audit/checks/__init__.py
latency_audit/checks/clock.py
latency_audit/checks/cpu.py
latency_audit/checks/hardware.py
latency_audit/checks/kernel.py
latency_audit/checks/network.py
latency_audit/checks/process.py
latency_audit-0.1.4.dist-info/METADATA
latency_audit-0.1.4.dist-info/WHEEL
latency_audit-0.1.4.dist-info/entry_points.txt
latency_audit-0.1.4.dist-info/licenses/LICENSE
latency_audit-0.1.4.dist-info/RECORD
