Metadata-Version: 2.4
Name: latency-audit
Version: 0.1.4
Summary: HFT-grade Linux infrastructure validator. Audits kernel, CPU, network, and clock settings against trading latency best practices.
Project-URL: Homepage, https://github.com/padalan/latency-audit
Project-URL: Documentation, https://github.com/padalan/latency-audit#readme
Project-URL: Repository, https://github.com/padalan/latency-audit.git
Project-URL: Issues, https://github.com/padalan/latency-audit/issues
Project-URL: Changelog, https://github.com/padalan/latency-audit/releases
Author-email: Nikhil Padala <contact@nikhilpadala.com>
License: MIT
License-File: LICENSE
Keywords: audit,devops,hft,high-frequency-trading,infrastructure,latency,linux,performance,sysadmin,trading
Classifier: Development Status :: 4 - Beta
Classifier: Environment :: Console
Classifier: Intended Audience :: Developers
Classifier: Intended Audience :: Financial and Insurance Industry
Classifier: Intended Audience :: System Administrators
Classifier: License :: OSI Approved :: MIT License
Classifier: Operating System :: POSIX :: Linux
Classifier: Programming Language :: Python :: 3
Classifier: Programming Language :: Python :: 3.10
Classifier: Programming Language :: Python :: 3.11
Classifier: Programming Language :: Python :: 3.12
Classifier: Programming Language :: Python :: 3.13
Classifier: Topic :: System :: Benchmark
Classifier: Topic :: System :: Monitoring
Classifier: Topic :: System :: Systems Administration
Classifier: Typing :: Typed
Requires-Python: >=3.10
Requires-Dist: click>=8.0
Requires-Dist: rich>=13.0
Provides-Extra: dev
Requires-Dist: mypy>=1.0; extra == 'dev'
Requires-Dist: pre-commit>=3.0; extra == 'dev'
Requires-Dist: pytest-cov>=4.0; extra == 'dev'
Requires-Dist: pytest>=7.0; extra == 'dev'
Requires-Dist: ruff>=0.1.0; extra == 'dev'
